<entry identifier="p080r_3">
  <folio number="080r"
    url="http://gallica.bnf.fr/ark:/12148/btv1b10500001g/f165.item"/>

    <purpose type="observation"/>
    <activity type="weapon"/>

    <heading>Mortar</heading>

    <block>
      They make them of fine material and fine <material>copper</material> in the  shape of reinforced barrel, and which can hold 50 pounds of powder, and having made a clean hole in the ground at the foot of a wall, they embed the said loaded <tool>mortar</tool> in this hole, with the mouth on top, which will make a large breach.
    </block>

</entry>
