<entry identifier="p104v_a4">
<folio number="104v" url="http://gallica.bnf.fr/ark:/12148/btv1b10500001g/f214.image"/>
<purpose type="making"/>
  <annotations>
          <annotation url="https://drive.google.com/drive/folders/0BwJi-u8sfkVDaHBIVmRtMFRwZjg" title="Spinet playing by itself, fol. 104v (Hiebert)"/>
      </annotations>

<heading>Spinet playing by itself</heading>

<block><activity type="musical instrument-making"/>Make an axle surrounded with wheels pierced all around in their thickness and attach <material>feathers</material> as for a cittern or a spinet and arrange them according to the song you want it to play, leaving a suitable distance. And, turning the axle either by yourself or by a <tool>clock spring</tool>, your invention will effect itself.</block>

<figure identifier="fig_p104v_1" url="https://drive.google.com/open?id=0B9-oNrvWdlO5cWFSaUU5a2R6N2s" position="left-bottom"/>
</entry>
